{
   "reference" : "This data is used in the Instrumental Variables chapter of The Effect.",
   "usage" : "social_insure",
   "title" : "Data from \"Social Networks and the Decision to Insure\"",
   "description" : "Description\nThe social_insure data contains data from Jai, De Janvry, and Saoudlet (2015) on a two-round social network-based experiment on getting farmers to get insurance. See the paper for more details.",
   "parameters" : {
      "pre_takeup_rate" : "Takeup rate prior to experiment",
      "age" : "Household Characteristics - Age",
      "intensive" : "Whether or not was assigned to \"intensive\" experimental session (1 = yes)",
      "village" : "Administrative village",
      "takeup_survey" : "Whether farmer ended up purchasing insurance. (1 = yes)",
      "default" : "\"Default option\" in experimental format assigned to. (1 = default is to buy, 0 = default is to not buy)",
      "male" : "Household Caracteristics: Gender of Household Head (1 = male)",
      "address" : "Natural village",
      "disaster_prob" : "Perceived Probability of Disasters Next Year",
      "agpop" : "Household Characteristics - Household Size",
      "ricearea_2010" : "Area of Rice Production",
      "literacy" : "1 = literate, 0 = illiterate",
      "risk_averse" : "Risk aversion measurement"
   },
   "format" : "A data frame with 1410 rows and 13 variables"
}
