{
   "data" : {
      "y" : {
         "vars" : [
            "dat"
         ],
         "smps" : [
            "Smp1",
            "Smp2",
            "Smp3",
            "Smp4",
            "Smp5",
            "Smp6",
            "Smp7",
            "Smp8",
            "Smp9",
            "Smp10",
            "Smp11",
            "Smp12",
            "Smp13",
            "Smp14",
            "Smp15",
            "Smp16",
            "Smp17",
            "Smp18",
            "Smp19",
            "Smp20",
            "Smp21",
            "Smp22",
            "Smp23",
            "Smp24",
            "Smp25",
            "Smp26",
            "Smp27",
            "Smp28",
            "Smp29",
            "Smp30",
            "Smp31",
            "Smp32",
            "Smp33",
            "Smp34",
            "Smp35",
            "Smp36",
            "Smp37",
            "Smp38",
            "Smp39",
            "Smp40",
            "Smp41",
            "Smp42",
            "Smp43",
            "Smp44",
            "Smp45",
            "Smp46",
            "Smp47",
            "Smp48",
            "Smp49",
            "Smp50",
            "Smp51",
            "Smp52",
            "Smp53",
            "Smp54",
            "Smp55",
            "Smp56",
            "Smp57",
            "Smp58",
            "Smp59",
            "Smp60",
            "Smp61",
            "Smp62",
            "Smp63",
            "Smp64",
            "Smp65",
            "Smp66"
         ],
         "data" : [
            [
               28,
               -44,
               29,
               30,
               24,
               28,
               37,
               32,
               36,
               27,
               26,
               28,
               29,
               26,
               27,
               22,
               23,
               20,
               25,
               25,
               36,
               23,
               31,
               32,
               24,
               27,
               33,
               16,
               24,
               29,
               36,
               21,
               28,
               26,
               27,
               27,
               32,
               25,
               28,
               24,
               40,
               21,
               31,
               32,
               28,
               26,
               30,
               27,
               26,
               24,
               32,
               29,
               34,
               -2,
               25,
               19,
               36,
               29,
               30,
               22,
               28,
               33,
               39,
               25,
               16,
               23
            ]
         ]
      }
   },
   "info" : "<meta name=\"viewport\" content=\"width=device-width, initial-scale=1.0, user-scalable=yes\" />\n<script type=\"text/javascript\">\nconst macros = { \"\\\\R\": \"\\\\textsf{R}\", \"\\\\code\": \"\\\\texttt\"};\nfunction processMathHTML() {\n    var l = document.getElementsByClassName('reqn');\n    for (let e of l) { katex.render(e.textContent, e, { throwOnError: false, macros }); }\n    return;\n}</script>\n<script defer src=\"https://cdn.jsdelivr.net/npm/katex@0.15.3/dist/katex.min.js\"\n    onload=\"processMathHTML();\"></script>\n<table style=\"width: 100%;\"><tr><td>newcomb</td><td style=\"text-align: right;\">R Documentation</td></tr></table>\n<h2>\nNewcomb's Measurements of the Passage Time of Light\n</h2>\n<h3>Description</h3>\n<p>A numeric vector giving the &lsquo;Third Series&rsquo; of measurements of the\npassage time of light recorded by Newcomb in 1882.  The given values\ndivided by 1000 plus 24.8 give the time in millionths of a second for\nlight to traverse a known distance. The &lsquo;true&rsquo; value is now\nconsidered to be 33.02.\n</p>\n<p>The dataset is given in the order in Staudte and Sheather.  Stigler\n(1977, Table 5) gives the dataset as\n</p>\n<pre>\n    28 26 33 24 34 -44 27 16 40 -2 29 22 24 21 25 30 23 29 31 19\n    24 20 36 32 36 28 25 21 28 29 37 25 28 26 30 32 36 26 30 22\n    36 23 27 27 28 27 31 27 26 33 26 32 32 24 39 28 24 25 32 25\n    29 27 28 29 16 23\n</pre>\n<p>However, order is not relevant to its use as an example of robust\nestimation.  (Thanks to Anthony Unwin for bringing this difference to our\nattention.)\n</p>\n<h3>Usage</h3>\n<pre><code class='language-R'>newcomb\n</code></pre>\n<h3>Source</h3>\n<p>S. M. Stigler (1973)\nSimon Newcomb, Percy Daniell, and the history of robust estimation\n1885&ndash;1920.\n<em>Journal of the American Statistical Association</em> <b>68</b>, 872&ndash;879.\n</p>\n<p>S. M. Stigler (1977)\nDo robust estimators work with <em>real</em> data?\n<em>Annals of Statistics</em>, <b>5</b>, 1055&ndash;1098.\n</p>\n<p>R. G. Staudte and S. J. Sheather (1990)\n<em>Robust Estimation and Testing.</em> Wiley.\n</p>\n</main>\n</div>\n",
   "config" : {
      "graphType" : "Treemap",
      "title" : "Newcomb's Measurements of the Passage Time of Light",
      "subtitle" : "MASS - newcomb"
   }
}
