{
   "format" : "A data frame with columns:",
   "parameters" : {
      "status" : "dead or censored.",
      "treat" : "treatment: standard or test.",
      "diag.time" : "times since diagnosis in months at entry to trial.",
      "age" : "patient's age in years.",
      "cell" : "one of four cell types.",
      "prior" : "prior therapy?",
      "Karn" : "Karnofsky score of patient's performance on a scale of 0 to 100.",
      "stime" : "survival or follow-up time in days."
   },
   "reference" : "Kalbfleisch, J.D. and Prentice R.L. (1980)\nThe Statistical Analysis of Failure Time Data.\nWiley.",
   "usage" : "VA",
   "description" : "Description\nVeteran's Administration lung cancer trial from Kalbfleisch & Prentice.",
   "title" : "Veteran's Administration Lung Cancer Trial"
}
