{
   "info" : "<table width=\"100%\" summary=\"page for bushfire\"><tr><td>bushfire</td><td style=\"text-align: right;\">R Documentation</td></tr></table>\\n<h2> Campbell Bushfire Data </h2>\\n<h3>Description</h3>\\n<p>This data set was used by Campbell (1984) to locate bushfire scars.\\nThe dataset contains satelite measurements on five frequency bands,\\ncorresponding to each of 38 pixels.\\n</p>\\n<h3>Usage</h3>\\n<pre>data(bushfire)</pre>\\n<h3>Format</h3>\\n<p>A data frame with 38 observations on 5 variables.\\n</p>\\n<h3>Source</h3>\\n<p>Maronna, R.A. and Yohai, V.J. (1995)\\nThe Behavoiur of the Stahel-Donoho Robust Multivariate Estimator.\\n<em>Journal of the American Statistical Association</em> <b>90</b>, 330&ndash;341.\\n</p>\\n<h3>Examples</h3>\\n<pre>\\ndata(bushfire)\\nplot(bushfire)\\ncovMcd(bushfire)\\n</pre>\\n",
   "config" : {
      "subtitle" : "robustbase - bushfire",
      "graphType" : "Scatter2D",
      "title" : "Campbell Bushfire Data"
   },
   "data" : {
      "y" : {
         "smps" : [
            "Smp1",
            "Smp2",
            "Smp3",
            "Smp4",
            "Smp5",
            "Smp6",
            "Smp7",
            "Smp8",
            "Smp9",
            "Smp10",
            "Smp11",
            "Smp12",
            "Smp13",
            "Smp14",
            "Smp15",
            "Smp16",
            "Smp17",
            "Smp18",
            "Smp19",
            "Smp20",
            "Smp21",
            "Smp22",
            "Smp23",
            "Smp24",
            "Smp25",
            "Smp26",
            "Smp27",
            "Smp28",
            "Smp29",
            "Smp30",
            "Smp31",
            "Smp32",
            "Smp33",
            "Smp34",
            "Smp35",
            "Smp36",
            "Smp37",
            "Smp38"
         ],
         "data" : [
            [
               111,
               113,
               113,
               110,
               101,
               93,
               92,
               94,
               94,
               100,
               108,
               134,
               149,
               108,
               81,
               86,
               89,
               88,
               88,
               89,
               92,
               94,
               115,
               128,
               113,
               112,
               121,
               126,
               136,
               146,
               136,
               103,
               80,
               79,
               79,
               78,
               78,
               78
            ],
            [
               145,
               147,
               150,
               147,
               136,
               125,
               110,
               95,
               94,
               104,
               115,
               156,
               181,
               154,
               137,
               138,
               137,
               133,
               131,
               133,
               137,
               139,
               156,
               167,
               156,
               155,
               162,
               166,
               174,
               177,
               155,
               97,
               66,
               66,
               66,
               66,
               66,
               66
            ],
            [
               188,
               187,
               195,
               211,
               240,
               262,
               46,
               29,
               29,
               21,
               17,
               10,
               68,
               305,
               426,
               381,
               378,
               366,
               370,
               380,
               362,
               355,
               231,
               181,
               242,
               236,
               224,
               248,
               259,
               203,
               322,
               552,
               576,
               572,
               577,
               574,
               571,
               572
            ],
            [
               190,
               190,
               192,
               195,
               200,
               203,
               165,
               113,
               110,
               133,
               144,
               163,
               180,
               222,
               251,
               246,
               246,
               244,
               243,
               246,
               244,
               240,
               215,
               201,
               212,
               209,
               205,
               212,
               217,
               212,
               246,
               320,
               340,
               340,
               341,
               342,
               343,
               344
            ],
            [
               260,
               259,
               259,
               262,
               266,
               271,
               235,
               190,
               188,
               208,
               215,
               233,
               247,
               285,
               306,
               300,
               301,
               298,
               298,
               302,
               300,
               299,
               276,
               265,
               273,
               271,
               268,
               273,
               278,
               272,
               301,
               364,
               377,
               376,
               379,
               377,
               379,
               380
            ]
         ],
         "vars" : [
            "V1",
            "V2",
            "V3",
            "V4",
            "V5"
         ]
      }
   }
}
